fast_dash/Components.py
fast_dash/__init__.py
fast_dash/assets/favicon.ico
fast_dash/assets/markdown.css
fast_dash/cli.py
fast_dash/fast_dash.py
fast_dash/utils.py
fast_dash-0.2.14.dist-info/METADATA
fast_dash-0.2.14.dist-info/WHEEL
fast_dash-0.2.14.dist-info/entry_points.txt
fast_dash-0.2.14.dist-info/licenses/LICENSE
fast_dash-0.2.14.dist-info/RECORD
