Metadata-Version: 2.4
Name: fast_dash
Version: 0.2.14
Summary: Turn your Python functions into interactive web applications. Fast Dash is an innovative way to build and deploy your Python code as interactive apps with minimal changes to your original code.
License-Expression: MIT
License-File: LICENSE
Keywords: webdevelopment,python,machine-learning,data-science,data-visualization,dash
Author: Kedar Dabhadkar
Author-email: <kedar@fastdash.app>
Requires-Python: >=3.9,<3.14
Classifier: Development Status :: 4 - Beta
Classifier: Intended Audience :: Developers
Classifier: Topic :: Software Development :: Libraries :: Python Modules
Classifier: License :: OSI Approved :: MIT License
Classifier: Natural Language :: English
Classifier: Programming Language :: Python :: 3
Classifier: Programming Language :: Python :: 3.9
Classifier: Programming Language :: Python :: 3.10
Classifier: Programming Language :: Python :: 3.11
Classifier: Programming Language :: Python :: 3.12
Classifier: Programming Language :: Python :: 3.13
Provides-Extra: dev
Provides-Extra: doc
Provides-Extra: test
Requires-Dist: Pillow (>=9.2.0)
Requires-Dist: black ; extra == "test"
Requires-Dist: dash (>=2.11.0)
Requires-Dist: dash-bootstrap-components (>=2.0.0)
Requires-Dist: dash-iconify (>=0.1.2)
Requires-Dist: dash-mantine-components (>=1.0.0)
Requires-Dist: dash-socketio (>=1.1.1,<2.0.0)
Requires-Dist: dill (>=0.3.9,<0.4.0)
Requires-Dist: docstring-parser (>=0.15)
Requires-Dist: flake8 ; extra == "test"
Requires-Dist: flake8-docstrings ; extra == "test"
Requires-Dist: flask-socketio (>=5.5.1,<6.0.0)
Requires-Dist: griffe ; extra == "doc"
Requires-Dist: isort ; extra == "test"
Requires-Dist: livereload ; extra == "doc"
Requires-Dist: matplotlib (>=3.5.0)
Requires-Dist: mkdocs ; extra == "doc"
Requires-Dist: mkdocs-autorefs ; extra == "doc"
Requires-Dist: mkdocs-include-markdown-plugin ; extra == "doc"
Requires-Dist: mkdocs-jupyter ; extra == "doc"
Requires-Dist: mkdocs-material ; extra == "doc"
Requires-Dist: mkdocstrings-python ; extra == "doc"
Requires-Dist: pandas (>=1.0.0)
Requires-Dist: pre-commit ; extra == "dev"
Requires-Dist: pyreadline3 (>=3.5.4,<4.0.0)
Requires-Dist: pytest ; extra == "test"
Requires-Dist: pytest-cov ; extra == "test"
Requires-Dist: selenium ; extra == "test"
Requires-Dist: toml ; extra == "dev"
Requires-Dist: tox ; extra == "dev"
Requires-Dist: twine ; extra == "dev"
Requires-Dist: virtualenv ; extra == "dev"
